atexplain/__init__.py
atexplain/engine.py
atexplain-0.4.3.dist-info/licenses/LICENSE
atexplain-0.4.3.dist-info/METADATA
atexplain-0.4.3.dist-info/WHEEL
atexplain-0.4.3.dist-info/top_level.txt
atexplain-0.4.3.dist-info/RECORD
