Metadata-Version: 2.4
Name: atexplain
Version: 0.4.3
Summary: Библиотека для автоматического объяснения кода Python
Author: Mitay
License-Expression: MIT
Requires-Python: >=3.7
License-File: LICENSE
Dynamic: license-file
